Metadata-Version: 2.1
Name: pyqubo
Version: 1.5.0
Summary: PyQUBO allows you to create QUBOs or Ising models from mathematical expressions.
Home-page: https://github.com/recruit-communications/pyqubo
Download-URL: https://github.com/recruit-communications/pyqubo
Author: Recruit Co., Ltd.
Author-email: rco_pyqubo@ml.cocorou.jp
Maintainer: Recruit Co., Ltd.
Maintainer-email: rco_pyqubo@ml.cocorou.jp
License: Apache 2.0
Keywords: QUBO,quantum annealing,annealing machine,ising model,optimization
Classifier: Programming Language :: Python
Classifier: License :: OSI Approved :: Apache Software License
Requires-Python: >=3.8, <3.14
License-File: LICENSE
Requires-Dist: numpy>=1.17.3
Requires-Dist: dimod<0.13,>=0.9.14
Requires-Dist: dwave-neal>=0.5.7
Requires-Dist: Deprecated>=1.2.12
Requires-Dist: six>=1.15.0
